{
  "created_at": "2025-11-08T14:19:41.003317",
  "updated_at": "2025-11-08T14:19:41.003330",
  "id": "SOUL-4",
  "uuid": "eabe0993-0bd3-47f2-8bd7-579e7f1dc12a",
  "title": "Setup Ruff for linting and formatting",
  "description": "Configure Ruff for fast Python linting and code formatting. Setup ruff.toml with rules for code quality, import sorting, and formatting. Include pre-commit hook integration and IDE configuration files.",
  "status": "todo",
  "type": "task",
  "priority": "high",
  "labels": [],
  "reporter": "jared@goatbytes.io",
  "epic_id": "EPIC-001",
  "blocked_by": [],
  "blocks": [],
  "comments": [],
  "attachments": [],
  "attachment_count": 0,
  "comment_count": 0,
  "order": 0,
  "custom_fields": {}
}